{
    "test": [
        {
            "client": "test",
            "attribute": "test",
            "duedate": "",
            "ticketno": "test",
            "serialno": "test",
            "ettag": "test",
            "addnotes": "test",
            "type": "build"
        }
    ],
    "test_1": [
        {
            "client": "max size test",
            "attribute": "test",
            "duedate": "",
            "ticketno": "test",
            "serialno": "test",
            "ettag": "test",
            "addnotes": "this is a test to see how long the label history page will get",
            "type": "build"
        }
    ],
    "test_2": [
        {
            "client": "test",
            "attribute": "test",
            "duedate": "",
            "ticketno": "test",
            "serialno": "test",
            "ettag": "test",
            "addnotes": "test test test test test test test test test test test test test test test test test test test test test test test ",
            "type": "build"
        }
    ]
}